bootstrap_files/AWS/Dockerfile
bootstrap_files/AWS/__init__.py
bootstrap_files/AWS/expectation_suite.ipynb
bootstrap_files/AWS/lambda_function.py
bootstrap_files/AWS/requirements.txt
bootstrap_files/AWS/supporting_functions.py
bootstrap_files/AWS/testing_config.yml
bootstrap_files/AWS/non_verbose_files/expectation_suite.ipynb
bootstrap_files/AWS/non_verbose_files/lambda_function.py
bootstrap_files/AWS/terraform/buckets/data_bucket.tf
bootstrap_files/AWS/terraform/buckets/ge_buckets.tf
bootstrap_files/AWS/terraform/buckets/output.tf
bootstrap_files/AWS/terraform/buckets/variables.tf
bootstrap_files/AWS/terraform/lambda/lambda.tf
bootstrap_files/AWS/terraform/lambda/variables.tf
bootstrap_files/AWS/tutorial_files/get_tutorial_data.py
bootstrap_files/AWS/tutorial_files/lambda_function.py
bootstrap_files/AWS/tutorial_files/tutorial_notebook.ipynb
bootstrap_files/AWS/tutorial_files/terraform/buckets/data_bucket.tf
bootstrap_files/AWS/tutorial_files/terraform/lambda/lambda.tf
bootstrap_files/Azure/Dockerfile
bootstrap_files/Azure/expectation_suite.ipynb
bootstrap_files/Azure/requirements.txt
bootstrap_files/Azure/supporting_functions.py
bootstrap_files/Azure/testing_config.yml
bootstrap_files/Azure/function/host.json
bootstrap_files/Azure/function/local.settings.json
bootstrap_files/Azure/function/grater-expectations/function.json
bootstrap_files/Azure/function/grater-expectations/function.py
bootstrap_files/Azure/terraform/function/function.tf
bootstrap_files/Azure/terraform/function/resource_group.tf
bootstrap_files/Azure/terraform/function/variables.tf
bootstrap_files/Azure/terraform/storage/data_container.tf
bootstrap_files/Azure/terraform/storage/resource_group.tf
bootstrap_files/Azure/terraform/storage/storage.tf
bootstrap_files/Azure/terraform/storage/variables.tf
bootstrap_files/Azure/tutorial_files/get_tutorial_data.py
bootstrap_files/Azure/tutorial_files/tutorial_notebook.ipynb
bootstrap_files/Azure/tutorial_files/function/host.json
grater_expectations-1.2.2.dist-info/LICENSE
grater_expectations-1.2.2.dist-info/METADATA
grater_expectations-1.2.2.dist-info/WHEEL
grater_expectations-1.2.2.dist-info/entry_points.txt
grater_expectations-1.2.2.dist-info/top_level.txt
grater_expectations-1.2.2.dist-info/RECORD
