Metadata-Version: 2.1
Name: grater-expectations
Version: 1.2.2
Summary: A grated application of Great Expectations to create greater Expectations
Author-email: Jorik Schra <j.c.m.schra@gmail.com>
License: MIT License
Project-URL: Wiki, https://github.com/jschra/grater_expectations
Classifier: Programming Language :: Python :: 3
Classifier: Operating System :: OS Independent
Requires-Python: >=3.8
License-File: LICENSE
Requires-Dist: altair ==4.2.0
Requires-Dist: appnope ==0.1.2
Requires-Dist: argon2-cffi ==21.3.0
Requires-Dist: argon2-cffi-bindings ==21.2.0
Requires-Dist: asttokens ==2.0.5
Requires-Dist: attrs ==21.4.0
Requires-Dist: azure-common ==1.1.28
Requires-Dist: azure-core ==1.25.1
Requires-Dist: azure-identity ==1.11.0
Requires-Dist: azure-keyvault-secrets ==4.6.0
Requires-Dist: azure-mgmt-core ==1.3.2
Requires-Dist: azure-mgmt-storage ==20.1.0
Requires-Dist: azure-storage-blob ==12.13.1
Requires-Dist: backcall ==0.2.0
Requires-Dist: backports.zoneinfo ==0.2.1
Requires-Dist: beautifulsoup4 ==4.10.0
Requires-Dist: bleach ==4.1.0
Requires-Dist: boto3 ==1.21.28
Requires-Dist: botocore ==1.24.28
Requires-Dist: certifi ==2021.10.8
Requires-Dist: cffi ==1.15.0
Requires-Dist: charset-normalizer ==2.0.12
Requires-Dist: click ==8.1.0
Requires-Dist: colorama ==0.4.4
Requires-Dist: cryptography ==36.0.2
Requires-Dist: debugpy ==1.6.0
Requires-Dist: decorator ==5.1.1
Requires-Dist: defusedxml ==0.7.1
Requires-Dist: entrypoints ==0.4
Requires-Dist: executing ==0.8.3
Requires-Dist: great-expectations ==0.14.12
Requires-Dist: idna ==3.3
Requires-Dist: importlib-metadata ==4.11.3
Requires-Dist: importlib-resources ==5.6.0
Requires-Dist: ipykernel ==6.10.0
Requires-Dist: ipython ==8.2.0
Requires-Dist: ipython-genutils ==0.2.0
Requires-Dist: ipywidgets ==7.7.0
Requires-Dist: isodate ==0.6.1
Requires-Dist: jedi ==0.18.1
Requires-Dist: Jinja2 ==3.0.3
Requires-Dist: jmespath ==1.0.0
Requires-Dist: jsonpatch ==1.32
Requires-Dist: jsonpointer ==2.2
Requires-Dist: jsonschema ==4.4.0
Requires-Dist: jupyter-client ==7.2.0
Requires-Dist: jupyter-core ==4.9.2
Requires-Dist: jupyterlab-pygments ==0.1.2
Requires-Dist: jupyterlab-widgets ==1.1.0
Requires-Dist: MarkupSafe ==2.1.1
Requires-Dist: matplotlib-inline ==0.1.3
Requires-Dist: mistune ==0.8.4
Requires-Dist: msal ==1.19.0
Requires-Dist: msal-extensions ==1.0.0
Requires-Dist: msrest ==0.7.1
Requires-Dist: nbclient ==0.5.13
Requires-Dist: nbconvert ==6.4.5
Requires-Dist: nbformat ==5.2.0
Requires-Dist: nbopen ==0.6
Requires-Dist: nest-asyncio ==1.5.4
Requires-Dist: notebook ==6.4.10
Requires-Dist: numpy ==1.22.3
Requires-Dist: oauthlib ==3.2.1
Requires-Dist: packaging ==21.3
Requires-Dist: pandas ==1.4.1
Requires-Dist: pandocfilters ==1.5.0
Requires-Dist: parso ==0.8.3
Requires-Dist: pexpect ==4.8.0
Requires-Dist: pickleshare ==0.7.5
Requires-Dist: portalocker ==2.5.1
Requires-Dist: prometheus-client ==0.13.1
Requires-Dist: prompt-toolkit ==3.0.28
Requires-Dist: psutil ==5.9.0
Requires-Dist: ptyprocess ==0.7.0
Requires-Dist: pure-eval ==0.2.2
Requires-Dist: pycparser ==2.21
Requires-Dist: Pygments ==2.11.2
Requires-Dist: PyJWT ==2.5.0
Requires-Dist: pyparsing ==2.4.7
Requires-Dist: pyrsistent ==0.18.1
Requires-Dist: python-dateutil ==2.8.2
Requires-Dist: pytz ==2022.1
Requires-Dist: pytz-deprecation-shim ==0.1.0.post0
Requires-Dist: pyzmq ==22.3.0
Requires-Dist: requests ==2.27.1
Requires-Dist: requests-oauthlib ==1.3.1
Requires-Dist: ruamel.yaml ==0.17.17
Requires-Dist: ruamel.yaml.clib ==0.2.6
Requires-Dist: s3transfer ==0.5.2
Requires-Dist: scipy ==1.8.0
Requires-Dist: Send2Trash ==1.8.0
Requires-Dist: six ==1.16.0
Requires-Dist: soupsieve ==2.3.1
Requires-Dist: stack-data ==0.2.0
Requires-Dist: termcolor ==1.1.0
Requires-Dist: terminado ==0.13.3
Requires-Dist: testpath ==0.6.0
Requires-Dist: toolz ==0.11.2
Requires-Dist: tornado ==6.1
Requires-Dist: tqdm ==4.63.1
Requires-Dist: traitlets ==5.1.1
Requires-Dist: types-cryptography ==3.3.23
Requires-Dist: typing-extensions ==4.1.1
Requires-Dist: tzdata ==2022.1
Requires-Dist: tzlocal ==4.1
Requires-Dist: urllib3 ==1.26.9
Requires-Dist: wcwidth ==0.2.5
Requires-Dist: webencodings ==0.5.1
Requires-Dist: widgetsnbextension ==3.6.0
Requires-Dist: wincertstore ==0.2
Requires-Dist: zipp ==3.7.0
Requires-Dist: build ==0.8.0
Requires-Dist: setuptools >=61.0
